Codigos/ArbolSumadoresSegmentacion/Verilog/ArbolSumadoresSegmentacionVerilog.v
module ArbolSumadoresSegmentacion #(parameter WIDTH = 8) (
	input clk,
	input rstn,
	input [WIDTH-1:0] in0, in1, in2, in3, in4, in5, in6, in7,
	output reg [WIDTH+2:0] result // Resultado Final: suma de los 8 valores
);

//Etapas del pipeline o de la segmentacion
//Etapa 1: suma por pares
reg signed [WIDTH:0] stage1_0, stage1_1, stage1_2, stage1_3; //4 sumas de 9 bits

//Etapa 2: suma de sumas
reg signed [WIDTH+1:0] stage2_0, stage2_1; //2 sumas de 10 bits

//Etapa 3: suma final
reg signed [WIDTH+2:0] stage3; //Resultado final

always @(posedge clk or negedge rstn) begin
	if (!rstn) begin
		stage1_0 <= 0; stage1_1 <= 0; stage1_2 <= 0; stage1_3 <= 0;
		stage2_0 <= 0; stage2_1 <= 0;
		result <= 0;
	end else begin

		//Etapa 1
		stage1_0 <= $signed(in0) + $signed(in1);
		stage1_1 <= $signed(in2) + $signed(in3);
		stage1_2 <= $signed(in4) + $signed(in5);
		stage1_3 <= $signed(in6) + $signed(in7);

		//Etapa 2
		stage2_0 <= $signed(stage1_0) + $signed(stage1_1);
		stage2_1 <= $signed(stage1_2) + $signed(stage1_3);

		//Salida
		result <= stage2_0 + stage2_1;

	end
end

endmodule

Codigos/ArbolSumadoresSegmentacion/Verilog/tb_ArbolSumadoresSegmentacionVerilog.v
`timescale 1ps / 1ps

module tb_ArbolSumadoresSegmentacion;

	parameter WIDTH = 8;

	reg clk;
	reg rstn;
	reg signed [WIDTH-1:0] in0, in1, in2, in3, in4, in5, in6, in7;
	wire signed [WIDTH+2:0] result;

	ArbolSumadoresSegmentacion #(.WIDTH(WIDTH)) dut (
		.clk(clk),
		.rstn(rstn),
		.in0(in0), .in1(in1), .in2(in2), .in3(in3), 
		.in4(in4), .in5(in5), .in6(in6), .in7(in7),
		.result(result)
	);

	//Reloj de 1ps
	initial begin
		clk = 0;
		forever #1 clk = ~clk;
	end

	integer cycle;

	initial begin
        $dumpfile("ArbolSumadoresSegmentacionVerilogWave.vcd");
        $dumpvars(0, tb_ArbolSumadoresSegmentacion);

        // Reset
        rstn = 0;
        in0 = 0; in1 = 0; in2 = 0; in3 = 0;
        in4 = 0; in5 = 0; in6 = 0; in7 = 0;
        
        #2;
        rstn = 1;
        #2;

        $display("Empieza el test");
        // Test de segmentación: 4 sets de datos, uno por ciclo
        for (cycle = 0; cycle < 6; cycle = cycle + 1) begin
            case (cycle)
                0: begin
                    $display("Empieza a sumar el caso 1, resultado en 3 ciclos de 12");
                    in0 = 0; in1 = -1; in2 = 2; in3 = 3;
                    in4 = 4; in5 = 5; in6 = 6; in7 = -7; // 12
                end
                1: begin
                    $display("Empieza a sumar el caso 2, resultado en 3 ciclos de -1024");
                    in0 = -128; in1 = -128; in2 = -128; in3 = -128;
                    in4 = -128; in5 = -128; in6 = -128; in7 = -128; // -1024
                end
                2: begin
					$display("Empieza a sumar el caso 3, resultado en 3 ciclos de 125");
                    in0 = 10; in1 = 15; in2 = 20; in3 = 5;
                    in4 = 30; in5 = 25; in6 = 12; in7 = 8; // 125
                end
                3: begin
					$display("Empieza a sumar el caso 4, resultado en 3 ciclos de 1016");
                    in0 = 127; in1 = 127; in2 = 127; in3 = 127;
                    in4 = 127; in5 = 127; in6 = 127; in7 = 127; // 1016
                end
                default: begin
					$display("Caso por defecto, suma todo 0");
                    in0 = 0; in1 = 0; in2 = 0; in3 = 0;
                    in4 = 0; in5 = 0; in6 = 0; in7 = 0;
                end
            endcase

            #2;
            $display("Cycle %0d -> Resultado: %0d", cycle, result);
        end

        $finish;
    end
	
endmodule

Codigos/ArbolSumadoresSegmentacion/Verilog/ArbolSumadoresSegmentacionVerilogWave.vcd
$date
	Fri May 16 15:12:45 2025
$end
$version
	Icarus Verilog
$end
$timescale
	1ps
$end
$scope module tb_ArbolSumadoresSegmentacion $end
$var wire 11 ! result [10:0] $end
$var parameter 32 " WIDTH $end
$var reg 1 # clk $end
$var reg 8 $ in0 [7:0] $end
$var reg 8 % in1 [7:0] $end
$var reg 8 & in2 [7:0] $end
$var reg 8 ' in3 [7:0] $end
$var reg 8 ( in4 [7:0] $end
$var reg 8 ) in5 [7:0] $end
$var reg 8 * in6 [7:0] $end
$var reg 8 + in7 [7:0] $end
$var reg 1 , rstn $end
$var integer 32 - cycle [31:0] $end
$scope module dut $end
$var wire 1 # clk $end
$var wire 8 . in0 [7:0] $end
$var wire 8 / in1 [7:0] $end
$var wire 8 0 in2 [7:0] $end
$var wire 8 1 in3 [7:0] $end
$var wire 8 2 in4 [7:0] $end
$var wire 8 3 in5 [7:0] $end
$var wire 8 4 in6 [7:0] $end
$var wire 8 5 in7 [7:0] $end
$var wire 1 , rstn $end
$var parameter 32 6 WIDTH $end
$var reg 11 7 result [10:0] $end
$var reg 9 8 stage1_0 [8:0] $end
$var reg 9 9 stage1_1 [8:0] $end
$var reg 9 : stage1_2 [8:0] $end
$var reg 9 ; stage1_3 [8:0] $end
$var reg 10 < stage2_0 [9:0] $end
$var reg 10 = stage2_1 [9:0] $end
$upscope $end
$upscope $end
$enddefinitions $end
$comment Show the parameter values. $end
$dumpall
b1000 6
b1000 "
$end
#0
$dumpvars
b0 =
b0 <
b0 ;
b0 :
b0 9
b0 8
b0 7
b0 5
b0 4
b0 3
b0 2
b0 1
b0 0
b0 /
b0 .
bx -
0,
b0 +
b0 *
b0 )
b0 (
b0 '
b0 &
b0 %
b0 $
0#
b0 !
$end
#1
1#
#2
0#
1,
#3
1#
#4
0#
b11111001 +
b11111001 5
b110 *
b110 4
b101 )
b101 3
b100 (
b100 2
b11 '
b11 1
b10 &
b10 0
b11111111 %
b11111111 /
b0 -
#5
b111111111 ;
b1001 :
b101 9
b111111111 8
1#
#6
0#
b10000000 +
b10000000 5
b10000000 *
b10000000 4
b10000000 )
b10000000 3
b10000000 (
b10000000 2
b10000000 '
b10000000 1
b10000000 &
b10000000 0
b10000000 %
b10000000 /
b10000000 $
b10000000 .
b1 -
#7
b1000 =
b100 <
b100000000 ;
b100000000 :
b100000000 9
b100000000 8
1#
#8
0#
b1000 +
b1000 5
b1100 *
b1100 4
b11001 )
b11001 3
b11110 (
b11110 2
b101 '
b101 1
b10100 &
b10100 0
b1111 %
b1111 /
b1010 $
b1010 .
b10 -
#9
b1100 !
b1100 7
b1000000000 =
b1000000000 <
b10100 ;
b110111 :
b11001 9
b11001 8
1#
#10
0#
b1111111 +
b1111111 5
b1111111 *
b1111111 4
b1111111 )
b1111111 3
b1111111 (
b1111111 2
b1111111 '
b1111111 1
b1111111 &
b1111111 0
b1111111 %
b1111111 /
b1111111 $
b1111111 .
b11 -
#11
b10000000000 !
b10000000000 7
b1001011 =
b110010 <
b11111110 ;
b11111110 :
b11111110 9
b11111110 8
1#
#12
0#
b0 +
b0 5
b0 *
b0 4
b0 )
b0 3
b0 (
b0 2
b0 '
b0 1
b0 &
b0 0
b0 %
b0 /
b0 $
b0 .
b100 -
#13
b1111101 !
b1111101 7
b111111100 =
b111111100 <
b0 ;
b0 :
b0 9
b0 8
1#
#14
0#
b101 -
#15
b1111111000 !
b1111111000 7
b0 =
b0 <
1#
#16
0#
b110 -
