Codigos/maximoVectorPipelineRA/Verilog/maximoVectorVerilog.v
module max_pipeline_tree (
    input clk,
    input rst,
    input valid_in,
    input signed [7:0] data_in_1,  // Entrada de datos 1 (primer valor)
    input signed [7:0] data_in_2,  // Entrada de datos 2 (segundo valor)
    input signed [7:0] data_in_3,  // Entrada de datos 3
    input signed [7:0] data_in_4,  // Entrada de datos 4
    input signed [7:0] data_in_5,  // Entrada de datos 5
    input signed [7:0] data_in_6,  // Entrada de datos 6
    input signed [7:0] data_in_7,  // Entrada de datos 7
    input signed [7:0] data_in_8,  // Entrada de datos 8
    output reg signed [7:0] max_out,  // Resultado final del máximo
    output reg valid_out  // Señal de salida válida
);

    // Registros para almacenar los datos en las diferentes etapas del pipeline
    reg signed [7:0] stage_1_1, stage_1_2, stage_1_3, stage_1_4;
    reg signed [7:0] stage_2_1, stage_2_2;

    reg valid_stage_1, valid_stage_2;

    // Etapa 1: Comparación de pares (entrada directa)
    always @(posedge clk or posedge rst) begin
        if (rst) begin
            stage_1_1 <= 0;
            stage_1_2 <= 0;
            stage_1_3 <= 0;
            stage_1_4 <= 0;
            valid_stage_1 <= 0;
        end else if (valid_in) begin
		    stage_1_1 <= (data_in_1 > data_in_2) ? data_in_1 : data_in_2;
            stage_1_2 <= (data_in_3 > data_in_4) ? data_in_3 : data_in_4;
            stage_1_3 <= (data_in_5 > data_in_6) ? data_in_5 : data_in_6;
            stage_1_4 <= (data_in_7 > data_in_8) ? data_in_7 : data_in_8;
            valid_stage_1 <= 1;
        end
    end

    // Etapa 2: Comparación en pares de la etapa 1
    always @(posedge clk or posedge rst) begin
        if (rst) begin
            stage_2_1 <= 0;
            stage_2_2 <= 0;
            valid_stage_2 <= 0;
        end else if (valid_stage_1) begin
            stage_2_1 <= (stage_1_1 > stage_1_2) ? stage_1_1 : stage_1_2;
            stage_2_2 <= (stage_1_3 > stage_1_4) ? stage_1_3 : stage_1_4;
            valid_stage_2 <= 1;
        end
    end

    // Etapa 3: Comparación de los dos valores de la etapa 2 y Asignacion Final
    always @(posedge clk or posedge rst) begin
        if (rst) begin
            max_out <= 0;
            valid_out <= 0;
        end else if (valid_stage_2) begin
            max_out <= (stage_2_1 > stage_2_2) ? stage_2_1 : stage_2_2;
            valid_out <= 1;
        end else begin
            valid_out <= 0;
        end
    end

endmodule

Codigos/maximoVectorPipelineRA/Verilog/tb_maximoVectorVerilog.v
`timescale 1ps / 1ps

module tb_maximoVectorSegmentacion;

    // Declarar señales
    reg clk;
    reg rst;
    reg valid_in;
    reg signed [7:0] data_in_1;
    reg signed [7:0] data_in_2;
    reg signed [7:0] data_in_3;
    reg signed [7:0] data_in_4;
    reg signed [7:0] data_in_5;
    reg signed [7:0] data_in_6;
    reg signed [7:0] data_in_7;
    reg signed [7:0] data_in_8;
    wire signed [7:0] max_out;
    wire valid_out;

    integer cycle;

    // Instanciación del módulo a testear
    max_pipeline_tree uut (
        .clk(clk),
        .rst(rst),
        .valid_in(valid_in),
        .data_in_1(data_in_1),
        .data_in_2(data_in_2),
        .data_in_3(data_in_3),
        .data_in_4(data_in_4),
        .data_in_5(data_in_5),
        .data_in_6(data_in_6),
        .data_in_7(data_in_7),
        .data_in_8(data_in_8),
        .max_out(max_out),
        .valid_out(valid_out)
    );

    // Inicialización de señales
    initial begin
        $dumpfile("maximoVectorSegmentacionVerilogWave.vcd");
        $dumpvars(0, tb_maximoVectorSegmentacion);

        clk = 0;
        rst = 0;
        valid_in = 0;
        data_in_1 = 0;
        data_in_2 = 0;
        data_in_3 = 0;
        data_in_4 = 0;
        data_in_5 = 0;
        data_in_6 = 0;
        data_in_7 = 0;
        data_in_8 = 0;

        // Resetear el sistema
        rst = 1;
        #2 rst = 0;
        #2 valid_in = 1;  // Habilitar la entrada

        // Caso 1: Solo valores negativos
        // Vector: [-50, -20, -100, -5, -30, -90, -10, -60]
        data_in_1 = -50;
        data_in_2 = -20;
        data_in_3 = -100;
        data_in_4 = -5;
        data_in_5 = -30;
        data_in_6 = -90;
        data_in_7 = -10;
        data_in_8 = -60;

        #2;  // Esperar un ciclo de reloj

        // Verificar la salida
        $display("Ciclo 2 - Vector: [-50, -20, -100, -5, -30, -90, -10, -60]");
        $display("Max Output: %d, Valid Output: %b", max_out, valid_out);
        
        // Caso 2: Probar con valores negativos, cero y positivos
        // Vector: [-128, 0, 50, 120, -100, 50, 120, 127]
        data_in_1 = -128;  // Valor negativo mínimo
        data_in_2 = 0;     // Cero
        data_in_3 = 50;    // Valor positivo
        data_in_4 = 120;   // Valor positivo
        data_in_5 = -100;  // Valor negativo
        data_in_6 = 50;    // Valor positivo
        data_in_7 = 120;   // Valor positivo
        data_in_8 = 127;   // Valor positivo máximo

        #2;  // Esperar un ciclo de reloj

        // Verificar la salida
        $display("Ciclo 1 - Vector: [-128, 0, 50, 120, -100, 50, 120, 127]");
        $display("Max Output: %d, Valid Output: %b", max_out, valid_out);

        // Caso 3: Solo valores positivos
        // Vector: [30, 50, -80, 120, 0, 60, 70, 110]
        data_in_1 = 30;
        data_in_2 = 50;
        data_in_3 = -80;
        data_in_4 = 120;
        data_in_5 = 0;
        data_in_6 = 60;
        data_in_7 = 70;
        data_in_8 = 110;
       
        // Verificar la salida
        $display("Ciclo 3 - Vector: [30, 50, -80, 120, 0, 60, 70, 110]");
        $display("Max Output: %d, Valid Output: %b", max_out, valid_out);

        for (cycle = 4; cycle < 7; cycle = cycle + 1) begin
            #2;
            $display("Ciclo %d", cycle);
            $display("Max Output: %d, Valid Output: %b", max_out, valid_out);
        end
        $finish;
    end

    // Generación de reloj
    always #1 clk = ~clk;

endmodule

Codigos/maximoVectorPipelineRA/Verilog/maximoVectorSegmentacionVerilogWave.vcd
$date
	Fri May 16 17:20:33 2025
$end
$version
	Icarus Verilog
$end
$timescale
	1ps
$end
$scope module tb_maximoVectorSegmentacion $end
$var wire 1 ! valid_out $end
$var wire 8 " max_out [7:0] $end
$var reg 1 # clk $end
$var reg 8 $ data_in_1 [7:0] $end
$var reg 8 % data_in_2 [7:0] $end
$var reg 8 & data_in_3 [7:0] $end
$var reg 8 ' data_in_4 [7:0] $end
$var reg 8 ( data_in_5 [7:0] $end
$var reg 8 ) data_in_6 [7:0] $end
$var reg 8 * data_in_7 [7:0] $end
$var reg 8 + data_in_8 [7:0] $end
$var reg 1 , rst $end
$var reg 1 - valid_in $end
$var integer 32 . cycle [31:0] $end
$scope module uut $end
$var wire 1 # clk $end
$var wire 8 / data_in_1 [7:0] $end
$var wire 8 0 data_in_2 [7:0] $end
$var wire 8 1 data_in_3 [7:0] $end
$var wire 8 2 data_in_4 [7:0] $end
$var wire 8 3 data_in_5 [7:0] $end
$var wire 8 4 data_in_6 [7:0] $end
$var wire 8 5 data_in_7 [7:0] $end
$var wire 8 6 data_in_8 [7:0] $end
$var wire 1 , rst $end
$var wire 1 - valid_in $end
$var reg 8 7 max_out [7:0] $end
$var reg 8 8 stage_1_1 [7:0] $end
$var reg 8 9 stage_1_2 [7:0] $end
$var reg 8 : stage_1_3 [7:0] $end
$var reg 8 ; stage_1_4 [7:0] $end
$var reg 8 < stage_2_1 [7:0] $end
$var reg 8 = stage_2_2 [7:0] $end
$var reg 1 ! valid_out $end
$var reg 1 > valid_stage_1 $end
$var reg 1 ? valid_stage_2 $end
$upscope $end
$upscope $end
$enddefinitions $end
$comment Show the parameter values. $end
$dumpall
$end
#0
$dumpvars
0?
0>
b0 =
b0 <
b0 ;
b0 :
b0 9
b0 8
b0 7
b0 6
b0 5
b0 4
b0 3
b0 2
b0 1
b0 0
b0 /
bx .
0-
1,
b0 +
b0 *
b0 )
b0 (
b0 '
b0 &
b0 %
b0 $
0#
b0 "
0!
$end
#1
1#
#2
0#
0,
#3
1#
#4
0#
b11000100 +
b11000100 6
b11110110 *
b11110110 5
b10100110 )
b10100110 4
b11100010 (
b11100010 3
b11111011 '
b11111011 2
b10011100 &
b10011100 1
b11101100 %
b11101100 0
b11001110 $
b11001110 /
1-
#5
1>
b11110110 ;
b11100010 :
b11111011 9
b11101100 8
1#
#6
0#
b1111111 +
b1111111 6
b1111000 *
b1111000 5
b110010 )
b110010 4
b10011100 (
b10011100 3
b1111000 '
b1111000 2
b110010 &
b110010 1
b0 %
b0 0
b10000000 $
b10000000 /
#7
b1111111 ;
b110010 :
b1111000 9
b0 8
1?
b11110110 =
b11111011 <
1#
#8
0#
b100 .
b1101110 +
b1101110 6
b1000110 *
b1000110 5
b111100 )
b111100 4
b0 (
b0 3
b10110000 &
b10110000 1
b110010 %
b110010 0
b11110 $
b11110 /
#9
1!
b11111011 "
b11111011 7
b1111111 =
b1111000 <
b1101110 ;
b111100 :
b110010 8
1#
#10
0#
b101 .
#11
b1101110 =
b1111111 "
b1111111 7
1#
#12
0#
b110 .
#13
b1111000 "
b1111000 7
1#
#14
0#
b111 .
