Codigos/reconocedorPatrones/Verilog/reconocedorPatronesVerilog.v
module reconocedor_patrones (
    input wire clk,
    input wire rst,
    input wire in,
    output reg out
);


    parameter S0 = 3'b000; // Estado inicial
    parameter S1 = 3'b001; // Detecta '1'
    parameter S2 = 3'b010; // Detecta '10'
    parameter S3 = 3'b011; // Detecta '101'
    parameter S4 = 3'b100; // Detecta '1011'
   

    reg[2:0] state, next_state;

    always @(posedge clk or posedge rst) begin
        if (rst)
            state <= S0;
        else
            state <= next_state;
    end

    always @(*) begin
        out = 1'b0; // Salida por defecto
        case (state)
            S0: next_state = in ? S1 : S0;
            S1: next_state = in ? S1 : S2;
            S2: next_state = in ? S3 : S0;
            S3: next_state = in ? S4 : S2;
            S4: begin
                out = 1'b1;
                next_state = S1;
            end
            default: next_state = S0;
        endcase
    end

endmodule

Codigos/reconocedorPatrones/Verilog/tb_reconocerPatronesVerilog.v
`timescale 1ps / 1ps

module tb_reconocedorPatrones;

    // Señales
    reg clk;
    reg rst;
    reg in;
    wire out;

    // Instancia del módulo bajo prueba (UUT - Unit Under Test)
    reconocedor_patrones uut (
        .clk(clk),
        .rst(rst),
        .in(in),
        .out(out)
    );

    // Generador de reloj (período de 10 ns)
    always #1 clk = ~clk;

    task apply_input;
        input val;
        begin
            in = val;
            #2;
            $display("t=%0t | in=%b | out=%b", $time, in, out);
        end
    endtask

    // Proceso de prueba
    initial begin
        $dumpfile("reconocedorPatronesVerilogWave.vcd");
	    $dumpvars(0, tb_reconocedorPatrones);

        // Inicialización
        clk = 0;
        rst = 1;
        in = 0;
        #2; // Esperar 10 ns

        rst = 0; // Liberar el reset
        #2;

        $display("Inicio de test del reconocedor de patrones (buscando 1011):");
        
        // Primera prueba: 1011 (patrón correcto)
        apply_input(1); //S1
        apply_input(0); //S2
        apply_input(1); //S3
        apply_input(1); //S4 -> salida = 1
       

        // Segunda prueba: patrón parcial (101)
        apply_input(1); 
        apply_input(0); 
        apply_input(1); 

        //Tercera prueba: ruido + patrón correcto + superposicion
        apply_input(0); //Ruido
        apply_input(1); 
        apply_input(0); 
        apply_input(1); //superposicion
        apply_input(0); 
        apply_input(1); 
        apply_input(1); //salida -> 1

        $display("Test finalizado");
        $finish; // Finaliza la simulación
    end

endmodule

Codigos/reconocedorPatrones/Verilog/reconocedorPatronesVerilogWave.vcd
$date
	Fri May 16 14:57:49 2025
$end
$version
	Icarus Verilog
$end
$timescale
	1ps
$end
$scope module tb_reconocedorPatrones $end
$var wire 1 ! out $end
$var reg 1 " clk $end
$var reg 1 # in $end
$var reg 1 $ rst $end
$scope module uut $end
$var wire 1 " clk $end
$var wire 1 # in $end
$var wire 1 $ rst $end
$var parameter 3 % S0 $end
$var parameter 3 & S1 $end
$var parameter 3 ' S2 $end
$var parameter 3 ( S3 $end
$var parameter 3 ) S4 $end
$var reg 3 * next_state [2:0] $end
$var reg 1 ! out $end
$var reg 3 + state [2:0] $end
$upscope $end
$scope task apply_input $end
$var reg 1 , val $end
$upscope $end
$upscope $end
$enddefinitions $end
$comment Show the parameter values. $end
$dumpall
b100 )
b11 (
b10 '
b1 &
b0 %
$end
#0
$dumpvars
x,
b0 +
b0 *
1$
0#
0"
0!
$end
#1
1"
#2
0"
0$
#3
1"
#4
b1 *
0"
1#
1,
#5
b1 +
1"
#6
b10 *
0"
0#
0,
#7
b0 *
b10 +
1"
#8
b11 *
0"
1#
1,
#9
b100 *
b11 +
1"
#10
0"
#11
b1 *
1!
b100 +
1"
#12
0"
#13
0!
b1 +
1"
#14
b10 *
0"
0#
0,
#15
b0 *
b10 +
1"
#16
b11 *
0"
1#
1,
#17
b100 *
b11 +
1"
#18
b10 *
0"
0#
0,
#19
b0 *
b10 +
1"
#20
b11 *
0"
1#
1,
#21
b100 *
b11 +
1"
#22
b10 *
0"
0#
0,
#23
b0 *
b10 +
1"
#24
b11 *
0"
1#
1,
#25
b100 *
b11 +
1"
#26
b10 *
0"
0#
0,
#27
b0 *
b10 +
1"
#28
b11 *
0"
1#
1,
#29
b100 *
b11 +
1"
#30
0"
#31
b1 *
1!
b100 +
1"
