Codigos/producto_escalar_rust/Verilog/productoEscalarVerilog.v
module productoEscalar (
    input clk,              // Reloj
    input reset,            // Reset asincrónico
    input start,            // Señal de inicio del cálculo
    input [7:0] a,          // Entrada A (elemento del vector)
    input [7:0] b,          // Entrada B (elemento del vector)
    input valid,            // Señal de validez de los datos
    output reg [15:0] result, // Resultado acumulado
    output reg busy         // Indica si está ocupado
);

    reg [15:0] accumulator;  // Acumulador del resultado
    reg [3:0] counter;       // Contador de ciclos
    reg [3:0] max_count;     // Tamaño del vector - 1

    wire [15:0] producto;

    // Instanciamos el multiplicador tipo RustHDL
    mul8x8 mul_inst (
        .a(a),
        .b(b),
        .resul(producto)
    );

    always @(posedge clk or posedge reset) begin
        if (reset) begin
            accumulator <= 0;
            counter <= 0;
            result <= 0;
            busy <= 0;
            max_count <= 4;
        end else if (start && !busy) begin
            accumulator <= 0;
            counter <= 0;
            result <= 0;
            busy <= 1;
        end else if (busy) begin
            if (valid) begin
                accumulator <= accumulator + producto;
                counter <= counter + 1;
                if (counter == max_count) begin
                    result <= accumulator + producto;
                    busy <= 0;
                end
            end
        end
    end

    always @(*) begin
        if (counter == max_count) begin
            result <= accumulator;
            busy <= 0;
        end
end
endmodule

// Multiplicador estilo RustHDL (shift-and-add)
module mul8x8 (
    input [7:0] a,
    input [7:0] b,
    output reg [15:0] resul
);
    always @(*) begin
        resul = 16'd0;
        if (b[0]) resul = resul + (a << 0);
        if (b[1]) resul = resul + (a << 1);
        if (b[2]) resul = resul + (a << 2);
        if (b[3]) resul = resul + (a << 3);
        if (b[4]) resul = resul + (a << 4);
        if (b[5]) resul = resul + (a << 5);
        if (b[6]) resul = resul + (a << 6);
        if (b[7]) resul = resul + (a << 7);
    end
endmodule

Codigos/producto_escalar_rust/Verilog/tb_productoEscalarVerilog.v
`timescale 1ps / 1ps

module tb_productoEscalar;
    reg clk;
    reg reset;
    reg start;
    reg [7:0] a, b;
    reg valid;
    wire [15:0] result;
    wire busy;

    // Instanciamos el módulo bajo prueba
    productoEscalar uut (
        .clk(clk),
        .reset(reset),
        .start(start),
        .a(a),
        .b(b),
        .valid(valid),
        .result(result),
        .busy(busy)
    );

    // Generamos el reloj
    always begin
        #1 clk = ~clk; // Reloj con periodo de 10 unidades de tiempo
    end

    // Monitor para mostrar señales por consola
    initial begin
        $display("Tiempo | clk | reset | start | valid |   a   |   b   | busy |  result");
        $monitor("%5t   |  %b  |   %b   |   %b   |   %b   | %3d  | %3d  |  %b   | %5d", 
                  $time, clk, reset, start, valid, a, b, busy, result);
    end

    // Inicialización y prueba
    initial begin
        $dumpfile("productoEscalarVerilogWave.vcd");
	    $dumpvars(0, tb_productoEscalar);

        // Inicializamos las señales
        clk = 0;
        reset = 1;
        start = 0;
        valid = 0;
        a = 8'b0;
        b = 8'b0;

        // Esperamos un ciclo de reloj
        #2;
        reset = 0;

        // Iniciamos el cálculo
        start = 1;
        #2;
        
        start = 0;
        valid = 1;
        // Proporcionamos datos de entrada

        a = 8'd3;  // A[0] = 3
        b = 8'd4;  // B[0] = 4
        #2;
        a = 8'd5;  // A[1] = 5
        b = 8'd6;  // B[1] = 6
        #2;
        a = 8'd7;  // A[2] = 7
        b = 8'd8;  // B[2] = 8
        #2;
        a = 8'd9;  // A[3] = 9
        b = 8'd10; // B[3] = 10
        #2;

        // Mostramos el resultado
        $display("Resultado: %d", result);
        $finish;
    end
endmodule

Codigos/producto_escalar_rust/Verilog/productoEscalarVerilogWave.vcd
$date
	Sat May 17 16:59:07 2025
$end
$version
	Icarus Verilog
$end
$timescale
	1ps
$end
$scope module tb_productoEscalar $end
$var wire 16 ! result [15:0] $end
$var wire 1 " busy $end
$var reg 8 # a [7:0] $end
$var reg 8 $ b [7:0] $end
$var reg 1 % clk $end
$var reg 1 & reset $end
$var reg 1 ' start $end
$var reg 1 ( valid $end
$scope module uut $end
$var wire 8 ) a [7:0] $end
$var wire 8 * b [7:0] $end
$var wire 1 % clk $end
$var wire 1 & reset $end
$var wire 1 ' start $end
$var wire 1 ( valid $end
$var wire 16 + producto [15:0] $end
$var reg 16 , accumulator [15:0] $end
$var reg 1 " busy $end
$var reg 4 - counter [3:0] $end
$var reg 4 . max_count [3:0] $end
$var reg 16 / result [15:0] $end
$scope module mul_inst $end
$var wire 8 0 a [7:0] $end
$var wire 8 1 b [7:0] $end
$var reg 16 2 resul [15:0] $end
$upscope $end
$upscope $end
$upscope $end
$enddefinitions $end
$comment Show the parameter values. $end
$dumpall
$end
#0
$dumpvars
b0 2
b0 1
b0 0
b0 /
b100 .
b0 -
b0 ,
b0 +
b0 *
b0 )
0(
0'
1&
0%
b0 $
b0 #
0"
b0 !
$end
#1
1%
#2
0%
1'
0&
#3
1"
1%
#4
b1100 +
b1100 2
0%
b100 $
b100 *
b100 1
b11 #
b11 )
b11 0
1(
0'
#5
b1 -
b1100 ,
1%
#6
b11110 +
b11110 2
0%
b110 $
b110 *
b110 1
b101 #
b101 )
b101 0
#7
b10 -
b101010 ,
1%
#8
b111000 +
b111000 2
0%
b1000 $
b1000 *
b1000 1
b111 #
b111 )
b111 0
#9
b11 -
b1100010 ,
1%
#10
b1011010 +
b1011010 2
0%
b1010 $
b1010 *
b1010 1
b1001 #
b1001 )
b1001 0
#11
0"
b10111100 !
b10111100 /
b100 -
b10111100 ,
1%
